CHANGES.rst
MANIFEST.in
README.rst
setup.py
monolith/__init__.py
monolith.client.egg-info/PKG-INFO
monolith.client.egg-info/SOURCES.txt
monolith.client.egg-info/dependency_links.txt
monolith.client.egg-info/namespace_packages.txt
monolith.client.egg-info/not-zip-safe
monolith.client.egg-info/requires.txt
monolith.client.egg-info/top_level.txt
monolith/client/__init__.py
monolith/client/util.py
monolith/client/tests/__init__.py
monolith/client/tests/test_client.py
monolith/client/tests/test_util.py