Metadata-Version: 1.1
Name: monolith.client
Version: 0.9
Summary: Mozilla Monolith Client
Home-page: https://github.com/mozilla/monolith-client
Author: Mozilla Services
Author-email: services-dev@mozilla.org
License: Apache 2.0
Keywords: web services
Platform: UNKNOWN
Classifier: License :: OSI Approved :: Apache Software License
Classifier: Programming Language :: Python
Classifier: Programming Language :: Python :: 2
Classifier: Programming Language :: Python :: 2.6
Classifier: Programming Language :: Python :: 2.7
Classifier: Programming Language :: Python :: Implementation :: CPython
Classifier: Framework :: Pyramid
Classifier: Topic :: Internet :: WWW/HTTP
Classifier: Topic :: Internet :: WWW/HTTP :: WSGI :: Application
